<?xml version="1.0" encoding="UTF-8"?>
<odoo>
    <template id="report_saleorder_document_custom"
              inherit_id="sale.report_saleorder_document"
              priority="20">

        <xpath expr="//div[@id='informations']" position="inside">

            <!-- ==== 1) Van/tot event (df_startDatum / df_eindDatum) ==== -->
            <div t-if="doc.df_startDatum or doc.df_eindDatum" class="col">
                <strong>Van/tot event</strong>
                <div>

                    <!-- Start -->
                    <t t-if="doc.df_startDatum">
                        <span t-field="doc.df_startDatum"/>
                    </t>

                    <!-- Separator -->
                    <t t-if="doc.df_startDatum and doc.df_eindDatum">
                        <br/>
                        <span>tot</span>
                        <br/>
                    </t>

                    <!-- Einde -->
                    <t t-if="doc.df_eindDatum">
                        <span t-field="doc.df_eindDatum"/>
                    </t>

                </div>
            </div>


            <!-- ==== 2) Fallback: rental period ==== -->
            <div t-if="not doc.df_startDatum and not doc.df_eindDatum and (doc.rental_start_date or doc.rental_return_date)" class="col">
                <strong>Van/tot event</strong>
                <div>

                    <!-- Start -->
                    <t t-if="doc.rental_start_date">
                        <span t-field="doc.rental_start_date"/>
                    </t>

                    <!-- Separator -->
                    <t t-if="doc.rental_start_date and doc.rental_return_date">
                        <br/>
                        <span>tot</span>
                        <br/>
                    </t>

                    <!-- Einde -->
                    <t t-if="doc.rental_return_date">
                        <span t-field="doc.rental_return_date"/>
                    </t>

                </div>
            </div>


            <!-- ==== 3) Aantal personen ==== -->
            <div t-if="doc.x_studio_aantal_personen" class="col">
                <strong>Aantal personen</strong>
                <div>
                    <span t-field="doc.x_studio_aantal_personen"/>
                </div>
            </div>

        </xpath>
    </template>
</odoo>